{
  "core": "https://downloads.wordpress.org/release/wordpress-6.7.zip",
  "phpVersion": "8.1",
  "plugins": [
    "C:/Users/Posim/Downloads/elementor-patched/elementor",
    "C:/Users/Posim/Downloads/tpae-after/the-plus-addons-for-elementor-page-builder",
    "https://downloads.wordpress.org/plugin/query-monitor.zip"
  ],
  "testsEnvironment": false,
  "port": 8881,
  "config": {
    "WP_DEBUG": true,
    "WP_DEBUG_LOG": true,
    "WP_DEBUG_DISPLAY": false,
    "SAVEQUERIES": true,
    "SCRIPT_DEBUG": true
  }
}
